knowledge_distillation_framework/__init__.py
knowledge_distillation_framework/module.py
knowledge_distillation_framework-0.1.1.dist-info/LICENSE
knowledge_distillation_framework-0.1.1.dist-info/METADATA
knowledge_distillation_framework-0.1.1.dist-info/WHEEL
knowledge_distillation_framework-0.1.1.dist-info/top_level.txt
knowledge_distillation_framework-0.1.1.dist-info/RECORD
